CHANGELOG.md
pytrify/__init__.py
pytrify/errors.py
pytrify/immutable_wrapper.py
pytrify/list_view.py
pytrify/mutable_while_none.py
pytrify/set_once.py
pytrify-0.1.0a3.dist-info/LICENSE
pytrify-0.1.0a3.dist-info/WHEEL
pytrify-0.1.0a3.dist-info/METADATA
pytrify-0.1.0a3.dist-info/RECORD
